zoho_zeptomail/backend/__init__.py
zoho_zeptomail/backend/message.py
zoho_zeptomail/backend/zeptomail_backend.py
zoho_zeptomail/base/__init__.py
zoho_zeptomail/base/base.py
zoho_zeptomail/emails/__init__.py
django_zoho_zeptomail-0.0.3.dist-info/LICENSE.md
django_zoho_zeptomail-0.0.3.dist-info/METADATA
django_zoho_zeptomail-0.0.3.dist-info/WHEEL
django_zoho_zeptomail-0.0.3.dist-info/top_level.txt
django_zoho_zeptomail-0.0.3.dist-info/RECORD
