Metadata-Version: 2.1
Name: django-zoho-zeptomail
Version: 0.0.3
Summary: ZeptoMail for Django facilitates email sending from Django applications using ZeptoMail APIs.
Author-email: Zoho Mail <zmintegration@zohomail.com>
Classifier: Development Status :: 3 - Alpha
Classifier: Framework :: Django
Classifier: License :: OSI Approved :: MIT License
Classifier: Programming Language :: Python :: 3
Requires-Python: >=3.7
License-File: LICENSE.md
Requires-Dist: django
Requires-Dist: requests
